refreshpairlist/__init__.py
refreshpairlist/__main__.py
refreshpairlist/refresh_pairlist.py
refreshpairlist/schedule_pairlist_refresh.py
refreshpairlist-0.0.2.dist-info/LICENSE
refreshpairlist-0.0.2.dist-info/METADATA
refreshpairlist-0.0.2.dist-info/WHEEL
refreshpairlist-0.0.2.dist-info/entry_points.txt
refreshpairlist-0.0.2.dist-info/top_level.txt
refreshpairlist-0.0.2.dist-info/RECORD
