Metadata-Version: 2.1
Name: refreshpairlist
Version: 0.0.2
Summary: Dynamic Pairlist for FreqAI (freqtrade)
Author: mrzdev
License-File: LICENSE
Requires-Dist: requests-ratelimiter >=0.4.2
Requires-Dist: schedule >=1.2.1
